annlite/__init__.py
annlite/container.py
annlite/enums.py
annlite/executor.py
annlite/filter.py
annlite/helper.py
annlite/hnsw_bind.cp38-win_amd64.pyd
annlite/index.py
annlite/math.py
annlite/pq_bind.cp38-win_amd64.pyd
annlite/profile.py
annlite/utils.py
annlite/core/__init__.py
annlite/core/codec/__init__.py
annlite/core/codec/base.py
annlite/core/codec/pq.py
annlite/core/codec/projector.py
annlite/core/codec/vq.py
annlite/core/index/__init__.py
annlite/core/index/base.py
annlite/core/index/flat_index.py
annlite/core/index/pq_index.py
annlite/core/index/hnsw/__init__.py
annlite/core/index/hnsw/index.py
annlite/storage/__init__.py
annlite/storage/base.py
annlite/storage/kv.py
annlite/storage/table.py
annlite-0.4.0.dist-info/LICENSE
annlite-0.4.0.dist-info/METADATA
annlite-0.4.0.dist-info/WHEEL
annlite-0.4.0.dist-info/top_level.txt
annlite-0.4.0.dist-info/RECORD
