Metadata-Version: 2.1
Name: annlite
Version: 0.4.0
Summary: Fast and Light Approximate Nearest Neighbor Search Library integrated with the Jina Ecosystem
Home-page: https://github.com/jina-ai/annlite
Download-URL: https://github.com/jina-ai/pqlite/tags
Author: Jina AI
Author-email: team@jina.ai
License: Apache License 2.0
Keywords: product-quantization approximate-nearest-neighbor hnsw
Classifier: Intended Audience :: Developers
Classifier: Intended Audience :: Science/Research
Classifier: License :: OSI Approved :: Apache Software License
Classifier: Operating System :: OS Independent
Classifier: Programming Language :: Python :: 3.7
Classifier: Programming Language :: Python :: 3.8
Classifier: Programming Language :: Python :: 3.9
Classifier: Topic :: Scientific/Engineering :: Artificial Intelligence
Requires-Python: >=3.7
Provides-Extra: test
License-File: LICENSE
